creamas/__init__.py
creamas/agents.py
creamas/ds.py
creamas/features.py
creamas/grid.py
creamas/logging.py
creamas/mappers.py
creamas/math.py
creamas/mp.py
creamas/nx.py
creamas/serializers.py
creamas/util.py
creamas/vote.py
creamas/core/__init__.py
creamas/core/agent.py
creamas/core/artifact.py
creamas/core/environment.py
creamas/core/feature.py
creamas/core/mapper.py
creamas/core/rule.py
creamas/core/simulation.py
creamas/domains/__init__.py
creamas/domains/image/__init__.py
creamas/domains/image/features.py
creamas/domains/image/image.py
creamas/domains/image/gp/__init__.py
creamas/domains/image/gp/artifact.py
creamas/domains/image/gp/generator.py
creamas/domains/image/gp/primitives.py
creamas/domains/image/gp/tools.py
creamas/domains/text/__init__.py
creamas/examples/__init__.py
creamas/examples/grid/__init__.py
creamas/examples/grid/grid_agent.py
creamas/examples/grid/grid_node.py
creamas/examples/grid/main.py
creamas/examples/grid/ukko.py
creamas/examples/grid/utils.py
creamas/examples/spiro/__init__.py
creamas/examples/spiro/serializers.py
creamas/examples/spiro/spiro.py
creamas/examples/spiro/spiro_agent.py
creamas/examples/spiro/spiro_agent_mp.py
creamas/rules/__init__.py
creamas/rules/agent.py
creamas/rules/feature.py
creamas/rules/mapper.py
creamas/rules/rule.py
examples/__init__.py
examples/grid/__init__.py
examples/grid/grid_agent.py
examples/grid/grid_node.py
examples/grid/main.py
examples/grid/ukko.py
examples/grid/utils.py
examples/spiro/__init__.py
examples/spiro/serializers.py
examples/spiro/spiro.py
examples/spiro/spiro_agent.py
examples/spiro/spiro_agent_mp.py
creamas-0.5.0.dist-info/LICENSE
creamas-0.5.0.dist-info/METADATA
creamas-0.5.0.dist-info/WHEEL
creamas-0.5.0.dist-info/entry_points.txt
creamas-0.5.0.dist-info/top_level.txt
creamas-0.5.0.dist-info/RECORD
